examples/__init__.py
examples/app_cli_test.py
examples/app_crud_orm.py
examples/app_crud_sql.py
examples/quickstart.py
pf_flask_db/__init__.py
pf_flask_db/pf_app_database.py
pf_flask_db/pf_app_model.py
pf_flask_db/cli/__init__.py
pf_flask_db/cli/pf_flask_db_cli.py
pf_flask_db/common/__init__.py
pf_flask_db/common/pf_flask_db_exception.py
pf_flask_db/helper/__init__.py
pf_flask_db/helper/pf_db_helper.py
pf_flask_db/helper/pf_db_model.py
pf_flask_db/helper/query_suggestion.py
PF_Flask_DB-1.0.1.dist-info/LICENSE
PF_Flask_DB-1.0.1.dist-info/METADATA
PF_Flask_DB-1.0.1.dist-info/WHEEL
PF_Flask_DB-1.0.1.dist-info/top_level.txt
PF_Flask_DB-1.0.1.dist-info/RECORD
