Metadata-Version: 2.1
Name: PF-Flask-DB
Version: 1.0.1
Summary: Flask Database Manager by Problem Fighter Library
Home-page: https://github.com/problemfighter/pf-flask-db
Author: Problem Fighter
Author-email: problemfighter.com@gmail.com
License: Apache 2.0
Platform: any
Classifier: Intended Audience :: Developers
Classifier: License :: OSI Approved :: Apache Software License
Classifier: Programming Language :: Python
License-File: LICENSE
Requires-Dist: Flask
Requires-Dist: Flask-SQLAlchemy
Requires-Dist: PF-PY-Common
